{
    "user_id": "scott",
    "mask": true,
    "catalogs": [
        "datalake"
    ],
    "attributes": [
        {
            "content_world": "logistics",
            "classification": "sales",
            "filter_value": [
                5,
                6
            ]
        },
        {
            "content_world": "other",
            "classification": "personnel",
            "filter_value": [
                3
            ]
        },
        {
            "content_world": "logistics",
            "classification": "common"
        }
    ]
}